ProkaryoteAssembly/__init__.py
ProkaryoteAssembly/accessories.py
ProkaryoteAssembly/assemble.py
ProkaryoteAssembly/assemble_dir.py
ProkaryoteAssembly/config.py
ProkaryoteAssembly/prokaryote_assemble.py
ProkaryoteAssembly/prokaryote_assemble_dir.py
ProkaryoteAssembly-0.0.3.data/scripts/assemble.py
ProkaryoteAssembly-0.0.3.data/scripts/prokaryote_assemble.py
ProkaryoteAssembly-0.0.3.data/scripts/prokaryote_assemble_dir.py
ProkaryoteAssembly-0.0.3.dist-info/METADATA
ProkaryoteAssembly-0.0.3.dist-info/RECORD
ProkaryoteAssembly-0.0.3.dist-info/WHEEL
ProkaryoteAssembly-0.0.3.dist-info/top_level.txt
