Metadata-Version: 2.1
Name: ProkaryoteAssembly
Version: 0.0.3
Summary: Internal BFSSI package for assembling prokaryotic genomes from short reads
Home-page: https://github.com/bfssi-forest-dussault/ProkaryoteAssembly
Author: Forest Dussault
Author-email: forest.dussault@canada.ca
License: UNKNOWN
Platform: UNKNOWN
Requires-Dist: click
